[{"temp": 30, "VIN": 1, "lat": 34, "fuel": 100, "lng": 38, "speed": 10, "id": 1}, {"temp": 33, "VIN": 1, "lat": 35, "fuel": 98, "lng": 39, "speed": 15, "id": 2}, {"temp": 35, "VIN": 1, "lat": 36, "fuel": 95, "lng": 40, "speed": 20, "id": 3}, {"temp": 40, "VIN": 1, "lat": 37, "fuel": 94, "lng": 41, "speed": 30, "id": 4}, {"temp": 40, "VIN": 1, "lat": 38, "fuel": 92, "lng": 42, "speed": 40, "id": 5}, {"temp": 40, "VIN": 1, "lat": 39, "fuel": 30, "lng": 43, "speed": 40, "id": 6}, {"temp": 40, "VIN": 1, "lat": 40, "fuel": 30, "lng": 44, "speed": 40, "id": 7}, {"temp": 40, "VIN": 1, "lat": 41, "fuel": 30, "lng": 45, "speed": 50, "id": 8}, {"temp": 40, "VIN": 1, "lat": 42, "fuel": 30, "lng": 46, "speed": 55, "id": 9}, {"temp": 40, "VIN": 1, "lat": 43, "fuel": 30, "lng": 47, "speed": 60, "id": 10}, {"temp": 40, "VIN": 1, "lat": 44, "fuel": 30, "lng": 48, "speed": 65, "id": 11}, {"temp": 40, "VIN": 1, "lat": 45, "fuel": 30, "lng": 49, "speed": 60, "id": 12}, {"temp": 40, "VIN": 1, "lat": 46, "fuel": 30, "lng": 50, "speed": 60, "id": 13}, {"temp": 40, "VIN": 1, "lat": 47, "fuel": 30, "lng": 51, "speed": 55, "id": 14}, {"temp": 40, "VIN": 1, "lat": 48, "fuel": 30, "lng": 52, "speed": 50, "id": 15}, {"temp": 40, "VIN": 1, "lat": 49, "fuel": 30, "lng": 53, "speed": 55, "id": 16}, {"temp": 40, "VIN": 1, "lat": 50, "fuel": 30, "lng": 54, "speed": 20, "id": 17}, {"temp": 40, "VIN": 1, "lat": 51, "fuel": 30, "lng": 55, "speed": 20, "id": 18}, {"temp": 40, "VIN": 1, "lat": 52, "fuel": 30, "lng": 56, "speed": 20, "id": 19}, {"temp": 40, "VIN": 1, "lat": 53, "fuel": 30, "lng": 57, "speed": 20, "id": 20}, {"temp": 40, "VIN": 1, "lat": 54, "fuel": 30, "lng": 58, "speed": 20, "id": 21}, {"temp": 40, "VIN": 1, "lat": 55, "fuel": 30, "lng": 59, "speed": 20, "id": 22}, {"temp": 40, "VIN": 1, "lat": 56, "fuel": 30, "lng": 60, "speed": 20, "id": 23}, {"temp": 40, "VIN": 1, "lat": 57, "fuel": 30, "lng": 61, "speed": 20, "id": 24}, {"temp": 40, "VIN": 1, "lat": 58, "fuel": 30, "lng": 62, "speed": 20, "id": 25}, {"temp": 40, "VIN": 1, "lat": 59, "fuel": 30, "lng": 63, "speed": 20, "id": 26}, {"temp": 40, "VIN": 1, "lat": 60, "fuel": 30, "lng": 64, "speed": 20, "id": 27}, {"temp": 40, "VIN": 1, "lat": 61, "fuel": 30, "lng": 65, "speed": 20, "id": 28}, {"temp": 40, "VIN": 1, "lat": 62, "fuel": 30, "lng": 66, "speed": 20, "id": 29}, {"temp": 40, "VIN": 1, "lat": 63, "fuel": 24, "lng": 67, "speed": 20, "id": 30}]